{"id": "27792", "kind": "album", "title": "Sunny", "artist": "First Impression", "music": "Lyrics:", "lyrics": "Label:", "label": "Released: 31-12-2009", "released": "31-12-2009", "playtime": "", "plays": "", "cover": "https://lq.djjohal.com/covers/27792/Yaara Mere Yaara.jpg", "detail_url": "https://www.djjohal.com/album/27792/first-impression.html", "slug": "first-impression", "url_kind": "album", "mp3": {"stream": "", "kbps320": "", "kbps128": "", "kbps48": "", "zip320": "https://hd1.djjohal.com/download/zip/27792/320/First Impression.zip", "zip128": "https://hd.djjohal.com/download/zip/27792/128/First Impression.zip"}, "album_tracks": [{"id": "334485", "slug": "saah-suk-jande-sunny", "title": "Saah Suk Jande"}, {"id": "334486", "slug": "phoki-fadh-ne-sunny", "title": "Phoki Fadh Ne"}, {"id": "334487", "slug": "kali-sunny", "title": "Kali"}, {"id": "334488", "slug": "jhanjran-sunny", "title": "Jhanjran"}, {"id": "334489", "slug": "dil-mileyan-di-gall-sunny", "title": "Dil Mileyan Di Gall"}, {"id": "334490", "slug": "saunh-rabb-di-sunny", "title": "Saunh Rabb Di"}, {"id": "334491", "slug": "manka-sunny", "title": "Manka"}, {"id": "334492", "slug": "yaara-mere-yaara-sunny", "title": "Yaara Mere Yaara"}], "youtube_url": "", "first_seen_at": "2026-05-25T18:19:29+00:00", "last_seen_at": "2026-05-29T21:43:30+00:00"}