{"id": "4387", "kind": "album", "title": "Didar Sandhu", "artist": "Jija Jhanjran Liyade", "music": "Lyrics:", "lyrics": "Label:", "label": "Released: 30-11--0001", "released": "30-11--0001", "playtime": "", "plays": "", "cover": "https://lq.djjohal.com/covers/4387/Aaja Roti Khaa Ley Mittra.jpg", "detail_url": "https://www.djjohal.com/album/4387/jija-jhanjran-liyade.html", "slug": "jija-jhanjran-liyade", "url_kind": "album", "mp3": {"stream": "", "kbps320": "", "kbps128": "", "kbps48": "", "zip320": "https://hd1.djjohal.com/download/zip/4387/320/Jija Jhanjran Liyade.zip", "zip128": "https://hd.djjohal.com/download/zip/4387/128/Jija Jhanjran Liyade.zip"}, "album_tracks": [{"id": "145827", "slug": "jija-jhanjran-liyade-didar-sandhu", "title": "Jija Jhanjran Liyade"}, {"id": "145828", "slug": "raund-vangoo-hikk-chon-didar-sandhu", "title": "Raund Vangoo Hikk 'Chon"}, {"id": "145829", "slug": "teri-chappni-vagaah-ke-maarange-didar-sandhu", "title": "Teri Chappni Vagaah Ke Maarange"}, {"id": "145830", "slug": "teesee-uuton-digey-bair-didar-sandhu", "title": "Teesee Uuton Digey Bair"}, {"id": "145831", "slug": "aashiq-da-sir-neenva-didar-sandhu", "title": "Aashiq Da Sir Neenva"}, {"id": "145832", "slug": "peg-mangda-daru-da-didar-sandhu", "title": "Peg Mangda Daru Da"}, {"id": "145833", "slug": "assin-saun-mahine-varge-didar-sandhu", "title": "Assin Saun Mahine Varge"}, {"id": "145834", "slug": "akhh-bachake-tun-seeney-naal-didar-sandhu", "title": "Akhh Bachake Tun Seeney Naal"}, {"id": "145835", "slug": "tappe-boliyaan-didar-sandhu", "title": "Tappe-Boliyaan"}, {"id": "145836", "slug": "aaja-roti-khaa-ley-mittra-didar-sandhu", "title": "Aaja Roti Khaa Ley Mittra"}], "youtube_url": "", "first_seen_at": "2026-05-25T18:19:29+00:00", "last_seen_at": "2026-05-31T13:11:07+00:00"}