{"id": "4858", "kind": "album", "title": "A Tribute To Surjit Bindrakhia", "artist": "Surjit Bindrakhia", "music": "Lyrics:", "lyrics": "Label:", "label": "Released: 30-11--0001", "released": "30-11--0001", "playtime": "", "plays": "", "cover": "https://lq.djjohal.com/covers/4858/Mundri Nishaani.jpg", "detail_url": "https://www.djjohal.com/album/4858/a-tribute-to-surjit-bindrakhia.html", "slug": "a-tribute-to-surjit-bindrakhia", "url_kind": "album", "mp3": {"stream": "", "kbps320": "", "kbps128": "", "kbps48": "", "zip320": "https://hd1.djjohal.com/download/zip/4858/320/A Tribute To Surjit Bindrakhia.zip", "zip128": "https://hd.djjohal.com/download/zip/4858/128/A Tribute To Surjit Bindrakhia.zip"}, "album_tracks": [{"id": "150072", "slug": "main-kal-takk-nahin-rehna-surjit-bindrakhia", "title": "Main Kal Takk Nahin Rehna"}, {"id": "150073", "slug": "panchhi-udd-gaye-ne-surjit-bindrakhia", "title": "Panchhi Udd Gaye Ne"}, {"id": "150074", "slug": "hor-kujh-ho-gayee-surjit-bindrakhia", "title": "Hor Kujh Ho Gayee"}, {"id": "150075", "slug": "rove-saari-raat-surjit-bindrakhia", "title": "Rove Saari Raat"}, {"id": "150076", "slug": "koka-arthi-surjit-bindrakhia", "title": "Koka Arthi"}, {"id": "150077", "slug": "pind-diyaan-galiyaan-surjit-bindrakhia", "title": "Pind Diyaan Galiyaan"}, {"id": "150078", "slug": "lag-gaiyaan-pabandiyaan-surjit-bindrakhia", "title": "Lag Gaiyaan Pabandiyaan"}, {"id": "150079", "slug": "gudiyaan-ishq-diyaan-surjit-bindrakhia", "title": "Gudiyaan Ishq Diyaan"}, {"id": "150080", "slug": "yaar-tera-mangeya-gaya-surjit-bindrakhia", "title": "Yaar Tera Mangeya Gaya"}, {"id": "150081", "slug": "jitthe-marzi-jaa-surjit-bindrakhia", "title": "Jitthe Marzi Jaa"}, {"id": "150082", "slug": "mundri-nishaani-surjit-bindrakhia", "title": "Mundri Nishaani"}], "youtube_url": "", "first_seen_at": "2026-05-25T18:19:29+00:00", "last_seen_at": "2026-05-31T13:11:07+00:00"}