{"id": "729889", "kind": "album", "title": "Next Level - EP", "artist": "Flop Likhari", "music": "Raka", "lyrics": "Flop Likhari", "label": "Urban Pendu Records", "released": "06-05-2023", "playtime": "", "plays": "", "cover": "https://lq.djjohal.com/covers/729889/Vehle.jpg", "detail_url": "https://www.djjohal.com/album/729889/next-level-ep.html", "slug": "next-level-ep", "url_kind": "album", "mp3": {"stream": "", "kbps320": "", "kbps128": "", "kbps48": "", "zip320": "https://hd1.djjohal.com/download/zip/729889/320/Next Level - EP.zip", "zip128": "https://hd.djjohal.com/download/zip/729889/128/Next Level - EP.zip"}, "album_tracks": [{"id": "516173", "slug": "baba-damru-wala-flop-likhari", "title": "Baba Damru Wala"}, {"id": "516174", "slug": "goli-vatt-ke-flop-likhari", "title": "Goli Vatt Ke"}, {"id": "516175", "slug": "next-level-flop-likhari", "title": "Next Level"}, {"id": "516176", "slug": "vehle-flop-likhari", "title": "Vehle"}], "first_seen_at": "2026-05-24T23:32:47+00:00", "last_seen_at": "2026-05-24T23:32:47+00:00"}