{"id": "25004", "kind": "album", "title": "Amrita Virk", "artist": "Teriyan Nishaniyan", "music": "Lyrics:", "lyrics": "Label:", "label": "Released: 31-12-2008", "released": "31-12-2008", "playtime": "", "plays": "", "cover": "https://lq.djjohal.com/covers/25004/Milno Reh Gaya.jpg", "detail_url": "https://www.djjohal.com/album/25004/teriyan-nishaniyan.html", "slug": "teriyan-nishaniyan", "url_kind": "album", "mp3": {"stream": "", "kbps320": "", "kbps128": "", "kbps48": "", "zip320": "https://hd1.djjohal.com/download/zip/25004/320/Teriyan Nishaniyan.zip", "zip128": "https://hd.djjohal.com/download/zip/25004/128/Teriyan Nishaniyan.zip"}, "album_tracks": [{"id": "308184", "slug": "mahi-ne-nachaya-amrita-virk", "title": "Mahi Ne Nachaya"}, {"id": "308185", "slug": "mitthe-mitthe-lareyan-de-naal-amrita-virk", "title": "Mitthe Mitthe Lareyan De Naal"}, {"id": "308186", "slug": "haye-jawani-chadh-gayi-amrita-virk", "title": "Haye Jawani Chadh Gayi"}, {"id": "308187", "slug": "nachna-peya-amrita-virk", "title": "Nachna Peya"}, {"id": "308188", "slug": "gootha-parnot-utte-laa-de-amrita-virk", "title": "Gootha Parnot Utte Laa De"}, {"id": "308189", "slug": "teriyan-nishaniyan-ch-amrita-virk", "title": "Teriyan Nishaniyan Ch"}, {"id": "308190", "slug": "ajj-kal-teriyan-nazraan-amrita-virk", "title": "Ajj Kal Teriyan Nazraan"}, {"id": "308191", "slug": "kann-kar-gal-sun-amrita-virk", "title": "Kann Kar Gal Sun"}, {"id": "308192", "slug": "saanu-milda-gilda-reh-amrita-virk", "title": "Saanu Milda Gilda Reh"}, {"id": "308193", "slug": "milno-reh-gaya-amrita-virk", "title": "Milno Reh Gaya"}], "youtube_url": "", "first_seen_at": "2026-05-25T18:19:29+00:00", "last_seen_at": "2026-05-29T21:43:30+00:00"}