{"id": "720615", "kind": "single", "title": "Gold De Kangne", "artist": "Sukhman Heer", "music": "Rick Hrt", "lyrics": "Kaptaan", "label": "Jass Records", "released": "27-03-2020", "playtime": "02:54", "plays": "62391", "cover": "https://lq.djjohal.com/covers/720615/Gold De Kangne.jpg", "detail_url": "https://www.djjohal.com/single/720615/sukhman-heer-gold-de-kangne.html", "slug": "sukhman-heer-gold-de-kangne", "url_kind": "single", "mp3": {"stream": "https://dl2.djring.com/sd2.djjohal.com/128/504301/Gold De Kangne(DJJOhAL.Com).mp3", "kbps320": "https://hd1.djjohal.com/320/504301/Gold De Kangne - Sukhman Heer (DJJOhAL.Com).mp3", "kbps128": "https://sd2.djjohal.com/128/504301/Gold De Kangne - Sukhman Heer (DJJOhAL.Com).mp3", "kbps48": "https://lq.djjohal.com/48/504301/Gold De Kangne - Sukhman Heer (DJJOhAL.Com).mp3", "zip320": "https://hd1.djjohal.com/download/zip/720615/320/Gold De Kangne.zip", "zip128": "https://hd.djjohal.com/download/zip/720615/128/Gold De Kangne.zip"}, "album_tracks": [], "youtube_url": "", "first_seen_at": "2026-05-25T18:19:29+00:00", "last_seen_at": "2026-05-27T02:11:42+00:00"}