{"id": "463124", "kind": "single", "title": "Masley Real Issues", "artist": "2015 The Album", "music": "Lyrics:", "lyrics": "Label:", "label": "Released: 29-07-2015", "released": "29-07-2015", "playtime": "04:31", "plays": "20043", "cover": "https://lq.djjohal.com/covers/47243/Masley Real Issues.jpg", "detail_url": "https://www.djjohal.com/get/463124/masley-real-issues-deep-singha.html", "slug": "masley-real-issues-deep-singha", "url_kind": "get", "mp3": {"stream": "https://dl2.djring.com/sd2.djjohal.com/128/463124/Masley Real Issues(DJJOhAL.Com).mp3", "kbps320": "https://hd1.djjohal.com/320/463124/Masley Real Issues - Deep Singha (DJJOhAL.Com).mp3", "kbps128": "https://sd2.djjohal.com/128/463124/Masley Real Issues - Deep Singha (DJJOhAL.Com).mp3", "kbps48": "https://lq.djjohal.com/48/463124/Masley Real Issues - Deep Singha (DJJOhAL.Com).mp3", "zip320": "", "zip128": ""}, "album_tracks": [], "youtube_url": "https://www.youtube.com/watch?v=OVQ3Ng3i6IA", "first_seen_at": "2026-05-27T21:57:21+00:00", "last_seen_at": "2026-05-28T01:55:33+00:00"}