{"id": "727496", "kind": "single", "title": "Show", "artist": "Pavvy Virk", "music": "Rikhi", "lyrics": "Gumnaam Galib", "label": "Sirra Entertainment", "released": "01-06-2022", "playtime": "02:34", "plays": "7353", "cover": "https://lq.djjohal.com/covers/727496/Show.jpg", "detail_url": "https://www.djjohal.com/single/727496/pavvy-virk-show.html", "slug": "pavvy-virk-show", "url_kind": "single", "mp3": {"stream": "https://dl2.djring.com/sd2.djjohal.com/128/512873/Show(DJJOhAL.Com).mp3", "kbps320": "https://hd1.djjohal.com/320/512873/Show - Pavvy Virk (DJJOhAL.Com).mp3", "kbps128": "https://sd2.djjohal.com/128/512873/Show - Pavvy Virk (DJJOhAL.Com).mp3", "kbps48": "https://lq.djjohal.com/48/512873/Show - Pavvy Virk (DJJOhAL.Com).mp3", "zip320": "https://hd1.djjohal.com/download/zip/727496/320/Show.zip", "zip128": "https://hd.djjohal.com/download/zip/727496/128/Show.zip"}, "album_tracks": [], "youtube_url": "", "first_seen_at": "2026-05-25T18:19:29+00:00", "last_seen_at": "2026-05-26T14:37:34+00:00"}