{"id": "725893", "kind": "single", "title": "Toofan", "artist": "Sonu Dharamshot", "music": "The Vampire", "lyrics": "Nanna Nihalkheria", "label": "BMS Studio Music", "released": "07-01-2022", "playtime": "02:43", "plays": "5583", "cover": "https://lq.djjohal.com/covers/725893/Toofan.jpg", "detail_url": "https://www.djjohal.com/single/725893/sonu-dharamshot-toofan.html", "slug": "sonu-dharamshot-toofan", "url_kind": "single", "mp3": {"stream": "https://dl2.djring.com/sd2.djjohal.com/128/510869/Toofan(DJJOhAL.Com).mp3", "kbps320": "https://hd1.djjohal.com/320/510869/Toofan - Sonu Dharamshot (DJJOhAL.Com).mp3", "kbps128": "https://sd2.djjohal.com/128/510869/Toofan - Sonu Dharamshot (DJJOhAL.Com).mp3", "kbps48": "https://lq.djjohal.com/48/510869/Toofan - Sonu Dharamshot (DJJOhAL.Com).mp3", "zip320": "https://hd1.djjohal.com/download/zip/725893/320/Toofan.zip", "zip128": "https://hd.djjohal.com/download/zip/725893/128/Toofan.zip"}, "album_tracks": [], "youtube_url": "", "first_seen_at": "2026-05-25T18:19:29+00:00", "last_seen_at": "2026-05-26T17:28:18+00:00"}