{"id": "736536", "kind": "single", "title": "Preet Pablo", "artist": "Mera Naa Pegg Bna", "music": "Triangle Music", "lyrics": "Preet Pablo", "label": "Preet Pablo Music", "released": "26-04-2026", "playtime": "02:16", "plays": "3256", "cover": "https://lq.djjohal.com/covers/736536/Mera Naa Pegg Bna.jpg", "detail_url": "https://www.djjohal.com/single/736536/preet-pablo-mera-naa-pegg-bna.html", "slug": "preet-pablo-mera-naa-pegg-bna", "url_kind": "single", "mp3": {"stream": "https://dl2.djring.com/sd2.djjohal.com/128/526150/Mera Naa Pegg Bna(DJJOhAL.Com).mp3", "kbps320": "https://hd1.djjohal.com/320/526150/Mera Naa Pegg Bna - Preet Pablo (DJJOhAL.Com).mp3", "kbps128": "https://sd2.djjohal.com/128/526150/Mera Naa Pegg Bna - Preet Pablo (DJJOhAL.Com).mp3", "kbps48": "https://lq.djjohal.com/48/526150/Mera Naa Pegg Bna - Preet Pablo (DJJOhAL.Com).mp3", "zip320": "https://hd1.djjohal.com/download/zip/736536/320/Mera Naa Pegg Bna.zip", "zip128": "https://hd.djjohal.com/download/zip/736536/128/Mera Naa Pegg Bna.zip"}, "album_tracks": [], "first_seen_at": "2026-05-25T00:10:55+00:00", "last_seen_at": "2026-05-25T00:10:55+00:00"}