{"id": "385795", "kind": "single", "title": "Lubane Di Gaddi", "artist": "One Four Three (143)", "music": "", "lyrics": "", "label": "", "released": "", "playtime": "", "plays": "", "cover": "https://lq.djjohal.com/covers/cover/Lubane Di Gaddi.jpg", "detail_url": "https://www.djjohal.com/get/385795/lubane-di-gaddi-love-singh-multani.html", "slug": "lubane-di-gaddi-love-singh-multani", "url_kind": "get", "mp3": {"stream": "", "kbps320": "", "kbps128": "", "kbps48": "", "zip320": "", "zip128": ""}, "album_tracks": [], "youtube_url": "https://www.youtube.com/watch?v=vRRLe41QzAA", "first_seen_at": "2026-05-29T02:03:13+00:00", "last_seen_at": "2026-05-29T17:35:10+00:00"}