{"id": "510365", "kind": "single", "title": "Ucheyan Gharan Diye Jaayie", "artist": "Sadiyan Gallan", "music": "Various Artists", "lyrics": "Various Artists", "label": "TDot Records", "released": "15-12-2021", "playtime": "03:33", "plays": "19101", "cover": "https://lq.djjohal.com/covers/725483/Ucheyan Gharan Diye Jaayie.jpg", "detail_url": "https://www.djjohal.com/get/510365/ucheyan-gharan-diye-jaayie-hustinder.html", "slug": "ucheyan-gharan-diye-jaayie-hustinder", "url_kind": "get", "mp3": {"stream": "https://dl2.djring.com/sd2.djjohal.com/128/510365/Ucheyan Gharan Diye Jaayie(DJJOhAL.Com).mp3", "kbps320": "https://hd1.djjohal.com/320/510365/Ucheyan Gharan Diye Jaayie - Hustinder (DJJOhAL.Com).mp3", "kbps128": "https://sd2.djjohal.com/128/510365/Ucheyan Gharan Diye Jaayie - Hustinder (DJJOhAL.Com).mp3", "kbps48": "https://lq.djjohal.com/48/510365/Ucheyan Gharan Diye Jaayie - Hustinder (DJJOhAL.Com).mp3", "zip320": "", "zip128": ""}, "album_tracks": [], "youtube_url": "https://www.youtube.com/watch?v=KVaa87DAchA", "first_seen_at": "2026-05-26T17:28:18+00:00", "last_seen_at": "2026-05-26T18:15:37+00:00"}