{"id": "733860", "kind": "single", "title": "Hu Jattiye", "artist": "Dilpreet Dhillon", "music": "Gur Sidhu", "lyrics": "Kaptaan", "label": "White Hill Music", "released": "30-01-2025", "playtime": "02:50", "plays": "33723", "cover": "https://lq.djjohal.com/covers/733860/Hu Jattiye.jpg", "detail_url": "https://www.djjohal.com/single/733860/dilpreet-dhillon-hu-jattiye.html", "slug": "dilpreet-dhillon-hu-jattiye", "url_kind": "single", "mp3": {"stream": "https://dl2.djring.com/sd2.djjohal.com/128/522048/Hu Jattiye(DJJOhAL.Com).mp3", "kbps320": "https://hd1.djjohal.com/320/522048/Hu Jattiye - Dilpreet Dhillon (DJJOhAL.Com).mp3", "kbps128": "https://sd2.djjohal.com/128/522048/Hu Jattiye - Dilpreet Dhillon (DJJOhAL.Com).mp3", "kbps48": "https://lq.djjohal.com/48/522048/Hu Jattiye - Dilpreet Dhillon (DJJOhAL.Com).mp3", "zip320": "https://hd1.djjohal.com/download/zip/733860/320/Hu Jattiye.zip", "zip128": "https://hd.djjohal.com/download/zip/733860/128/Hu Jattiye.zip"}, "album_tracks": [], "youtube_url": "", "first_seen_at": "2026-05-25T18:19:29+00:00", "last_seen_at": "2026-05-25T21:09:10+00:00"}