{"id": "120283", "kind": "single", "title": "De Meinu Mundri", "artist": "Sajjan Rus Gaye", "music": "", "lyrics": "", "label": "", "released": "", "playtime": "", "plays": "", "cover": "https://lq.djjohal.com/covers/cover/De Meinu Mundri.jpg", "detail_url": "https://www.djjohal.com/get/120283/de-meinu-mundri-naseebo-lal.html", "slug": "de-meinu-mundri-naseebo-lal", "url_kind": "get", "mp3": {"stream": "", "kbps320": "", "kbps128": "", "kbps48": "", "zip320": "", "zip128": ""}, "album_tracks": [], "youtube_url": "https://www.youtube.com/watch?v=oqGSaRl-LdU", "first_seen_at": "2026-06-01T06:59:06+00:00", "last_seen_at": "2026-06-01T17:14:28+00:00"}