{"id": "731344", "kind": "single", "title": "Punjabi Sangeet", "artist": "Kanwar Grewal", "music": "Rupin Kahlon", "lyrics": "Kanwar Grewal", "label": "RJBeats", "released": "05-01-2024", "playtime": "03:58", "plays": "9891", "cover": "https://lq.djjohal.com/covers/731344/Punjabi Sangeet.jpg", "detail_url": "https://www.djjohal.com/single/731344/kanwar-grewal-punjabi-sangeet.html", "slug": "kanwar-grewal-punjabi-sangeet", "url_kind": "single", "mp3": {"stream": "https://dl2.djring.com/sd2.djjohal.com/128/518415/Punjabi Sangeet(DJJOhAL.Com).mp3", "kbps320": "https://hd1.djjohal.com/320/518415/Punjabi Sangeet - Kanwar Grewal (DJJOhAL.Com).mp3", "kbps128": "https://sd2.djjohal.com/128/518415/Punjabi Sangeet - Kanwar Grewal (DJJOhAL.Com).mp3", "kbps48": "https://lq.djjohal.com/48/518415/Punjabi Sangeet - Kanwar Grewal (DJJOhAL.Com).mp3", "zip320": "https://hd1.djjohal.com/download/zip/731344/320/Punjabi Sangeet.zip", "zip128": "https://hd.djjohal.com/download/zip/731344/128/Punjabi Sangeet.zip"}, "album_tracks": [], "youtube_url": "", "first_seen_at": "2026-05-25T15:58:11+00:00", "last_seen_at": "2026-05-25T17:05:32+00:00"}