{"id": "732298", "kind": "single", "title": "Pyar Na Mukke", "artist": "Vicky Sandhu", "music": "MixSingh", "lyrics": "Vicky Sandhu", "label": "MixSingh Music", "released": "31-05-2024", "playtime": "03:44", "plays": "7548", "cover": "https://lq.djjohal.com/covers/732298/Pyar Na Mukke.jpg", "detail_url": "https://www.djjohal.com/single/732298/vicky-sandhu-pyar-na-mukke.html", "slug": "vicky-sandhu-pyar-na-mukke", "url_kind": "single", "mp3": {"stream": "https://dl2.djring.com/sd2.djjohal.com/128/519792/Pyar Na Mukke(DJJOhAL.Com).mp3", "kbps320": "https://hd1.djjohal.com/320/519792/Pyar Na Mukke - Vicky Sandhu (DJJOhAL.Com).mp3", "kbps128": "https://sd2.djjohal.com/128/519792/Pyar Na Mukke - Vicky Sandhu (DJJOhAL.Com).mp3", "kbps48": "https://lq.djjohal.com/48/519792/Pyar Na Mukke - Vicky Sandhu (DJJOhAL.Com).mp3", "zip320": "https://hd1.djjohal.com/download/zip/732298/320/Pyar Na Mukke.zip", "zip128": "https://hd.djjohal.com/download/zip/732298/128/Pyar Na Mukke.zip"}, "album_tracks": [], "youtube_url": "", "first_seen_at": "2026-05-25T15:58:11+00:00", "last_seen_at": "2026-05-25T16:59:17+00:00"}