{"id": "525951", "kind": "single", "title": "Judaiyan", "artist": "Kanth Kaler", "music": "Various Artists", "lyrics": "Various Artists", "label": "KK MUSIC", "released": "02-04-2026", "playtime": "03:22", "plays": "2812", "cover": "https://lq.djjohal.com/covers/736407/Judaiyan.jpg", "detail_url": "https://www.djjohal.com/get/525951/judaiyan-kanth-kaler.html", "slug": "judaiyan-kanth-kaler", "url_kind": "get", "mp3": {"stream": "https://dl2.djring.com/sd2.djjohal.com/128/525951/Judaiyan(DJJOhAL.Com).mp3", "kbps320": "https://hd1.djjohal.com/320/525951/Judaiyan - Kanth Kaler (DJJOhAL.Com).mp3", "kbps128": "https://sd2.djjohal.com/128/525951/Judaiyan - Kanth Kaler (DJJOhAL.Com).mp3", "kbps48": "https://lq.djjohal.com/48/525951/Judaiyan - Kanth Kaler (DJJOhAL.Com).mp3", "zip320": "", "zip128": ""}, "album_tracks": [], "youtube_url": "https://www.youtube.com/watch?v=PFqGmRMnuz0", "first_seen_at": "2026-05-25T00:10:55+00:00", "last_seen_at": "2026-05-25T05:41:39+00:00"}