{"id": "70459", "kind": "single", "title": "Surjit Khan", "artist": "Blue Blood Ft. JP", "music": "Madmix", "lyrics": "King Grewal", "label": "Headliner Records", "released": "22-03-2019", "playtime": "03:09", "plays": "199749", "cover": "https://lq.djjohal.com/covers/70459/Blue Blood Ft. JP.jpg", "detail_url": "https://www.djjohal.com/single/70459/surjit-khan-blue-blood-ft-jp.html", "slug": "surjit-khan-blue-blood-ft-jp", "url_kind": "single", "mp3": {"stream": "https://dl2.djring.com/sd2.djjohal.com/128/499392/Blue Blood Ft. JP(DJJOhAL.Com).mp3", "kbps320": "https://hd1.djjohal.com/320/499392/Blue Blood Ft. JP - Surjit Khan (DJJOhAL.Com).mp3", "kbps128": "https://sd2.djjohal.com/128/499392/Blue Blood Ft. JP - Surjit Khan (DJJOhAL.Com).mp3", "kbps48": "https://lq.djjohal.com/48/499392/Blue Blood Ft. JP - Surjit Khan (DJJOhAL.Com).mp3", "zip320": "https://hd1.djjohal.com/download/zip/70459/320/Blue Blood Ft. JP.zip", "zip128": "https://hd.djjohal.com/download/zip/70459/128/Blue Blood Ft. JP.zip"}, "album_tracks": [], "youtube_url": "", "first_seen_at": "2026-05-25T18:19:29+00:00", "last_seen_at": "2026-05-27T07:55:23+00:00"}