{"id": "150770", "kind": "single", "title": "Tu Kahdi Punjaban", "artist": "Maa Diye Laado", "music": "", "lyrics": "", "label": "", "released": "", "playtime": "", "plays": "", "cover": "https://lq.djjohal.com/covers/cover/Tu Kahdi Punjaban.jpg", "detail_url": "https://www.djjohal.com/get/150770/tu-kahdi-punjaban-maqbool.html", "slug": "tu-kahdi-punjaban-maqbool", "url_kind": "get", "mp3": {"stream": "", "kbps320": "", "kbps128": "", "kbps48": "", "zip320": "", "zip128": ""}, "album_tracks": [], "youtube_url": "https://www.youtube.com/watch?v=Po_vZJqi4ms", "first_seen_at": "2026-05-31T13:11:07+00:00", "last_seen_at": "2026-05-31T16:54:55+00:00"}