{"id": "43533", "kind": "single", "title": "Billy X", "artist": "Raatan Na Soye (feat Akash)", "music": "Lyrics:", "lyrics": "Label:", "label": "Released: 11-08-2014", "released": "11-08-2014", "playtime": "03:31", "plays": "64134", "cover": "https://lq.djjohal.com/covers/43533/Raatan Na Soye (feat Akash).jpg", "detail_url": "https://www.djjohal.com/single/43533/billy-x-raatan-na-soye-feat-akash.html", "slug": "billy-x-raatan-na-soye-feat-akash", "url_kind": "single", "mp3": {"stream": "https://dl2.djring.com/sd2.djjohal.com/128/450317/Raatan Na Soye (feat Akash)(DJJOhAL.Com).mp3", "kbps320": "https://hd1.djjohal.com/320/450317/Raatan Na Soye (feat Akash) - Billy X (DJJOhAL.Com).mp3", "kbps128": "https://sd2.djjohal.com/128/450317/Raatan Na Soye (feat Akash) - Billy X (DJJOhAL.Com).mp3", "kbps48": "https://lq.djjohal.com/48/450317/Raatan Na Soye (feat Akash) - Billy X (DJJOhAL.Com).mp3", "zip320": "https://hd1.djjohal.com/download/zip/43533/320/Raatan Na Soye (feat Akash).zip", "zip128": "https://hd.djjohal.com/download/zip/43533/128/Raatan Na Soye (feat Akash).zip"}, "album_tracks": [], "youtube_url": "", "first_seen_at": "2026-05-25T18:19:29+00:00", "last_seen_at": "2026-05-28T07:46:23+00:00"}