{"id": "510998", "kind": "single", "title": "Toffee Vargi Naar", "artist": "Ishq Garaari (Full Album 2013)", "music": "Various Artists", "lyrics": "Various Artists", "label": "Shemaroo Music", "released": "12-01-2022", "playtime": "03:06", "plays": "4413", "cover": "https://lq.djjohal.com/covers/725993/Toffee Vargi Naar.jpg", "detail_url": "https://www.djjohal.com/get/510998/toffee-vargi-naar-vinaypal-buttar.html", "slug": "toffee-vargi-naar-vinaypal-buttar", "url_kind": "get", "mp3": {"stream": "https://dl2.djring.com/sd2.djjohal.com/128/510998/Toffee Vargi Naar(DJJOhAL.Com).mp3", "kbps320": "https://hd1.djjohal.com/320/510998/Toffee Vargi Naar - Vinaypal Buttar (DJJOhAL.Com).mp3", "kbps128": "https://sd2.djjohal.com/128/510998/Toffee Vargi Naar - Vinaypal Buttar (DJJOhAL.Com).mp3", "kbps48": "https://lq.djjohal.com/48/510998/Toffee Vargi Naar - Vinaypal Buttar (DJJOhAL.Com).mp3", "zip320": "", "zip128": ""}, "album_tracks": [], "youtube_url": "https://www.youtube.com/watch?v=Hv1KB7YcB6s", "first_seen_at": "2026-05-26T17:28:18+00:00", "last_seen_at": "2026-05-26T18:15:37+00:00"}