{"id": "3667", "kind": "single", "title": "Doriya", "artist": "Laung Taviteriaan", "music": "", "lyrics": "", "label": "", "released": "", "playtime": "", "plays": "", "cover": "https://lq.djjohal.com/covers/cover/Doriya.jpg", "detail_url": "https://www.djjohal.com/get/3667/doriya-balkar-sidhu.html", "slug": "doriya-balkar-sidhu", "url_kind": "get", "mp3": {"stream": "", "kbps320": "", "kbps128": "", "kbps48": "", "zip320": "", "zip128": ""}, "album_tracks": [], "youtube_url": "https://www.youtube.com/watch?v=t-s3gowNVhU", "first_seen_at": "2026-06-01T06:59:06+00:00", "last_seen_at": "2026-06-01T22:29:33+00:00"}