{"id": "452811", "kind": "single", "title": "04 Kanian", "artist": "Truth (2014)", "music": "Lyrics:", "lyrics": "Label:", "label": "Released: 19-12-2014", "released": "19-12-2014", "playtime": "04:11", "plays": "16996", "cover": "https://lq.djjohal.com/covers/44271/04 Kanian.jpg", "detail_url": "https://www.djjohal.com/get/452811/04-kanian-harman-deep.html", "slug": "04-kanian-harman-deep", "url_kind": "get", "mp3": {"stream": "https://dl2.djring.com/sd2.djjohal.com/128/452811/04 Kanian(DJJOhAL.Com).mp3", "kbps320": "https://hd1.djjohal.com/320/452811/04 Kanian - Harman Deep (DJJOhAL.Com).mp3", "kbps128": "https://sd2.djjohal.com/128/452811/04 Kanian - Harman Deep (DJJOhAL.Com).mp3", "kbps48": "https://lq.djjohal.com/48/452811/04 Kanian - Harman Deep (DJJOhAL.Com).mp3", "zip320": "", "zip128": ""}, "album_tracks": [], "youtube_url": "https://www.youtube.com/watch?v=zY-Jp_iHYgc", "first_seen_at": "2026-05-28T06:15:10+00:00", "last_seen_at": "2026-05-28T07:46:23+00:00"}