{"id": "65073", "kind": "single", "title": "DJ Sanj & Jay Status", "artist": "Blue Label", "music": "DJ Sanj", "lyrics": "Jay Status", "label": "Moviebox Record Label", "released": "03-05-2018", "playtime": "03:18", "plays": "81444", "cover": "https://lq.djjohal.com/covers/65073/Blue Label.jpg", "detail_url": "https://www.djjohal.com/single/65073/dj-sanj-jay-status-blue-label.html", "slug": "dj-sanj-jay-status-blue-label", "url_kind": "single", "mp3": {"stream": "https://dl2.djring.com/sd2.djjohal.com/128/492153/Blue Label(DJJOhAL.Com).mp3", "kbps320": "https://hd1.djjohal.com/320/492153/Blue Label - DJ Sanj & Jay Status (DJJOhAL.Com).mp3", "kbps128": "https://sd2.djjohal.com/128/492153/Blue Label - DJ Sanj & Jay Status (DJJOhAL.Com).mp3", "kbps48": "https://lq.djjohal.com/48/492153/Blue Label - DJ Sanj & Jay Status (DJJOhAL.Com).mp3", "zip320": "https://hd1.djjohal.com/download/zip/65073/320/Blue Label.zip", "zip128": "https://hd.djjohal.com/download/zip/65073/128/Blue Label.zip"}, "album_tracks": [], "youtube_url": "", "first_seen_at": "2026-05-25T18:19:29+00:00", "last_seen_at": "2026-05-27T11:28:33+00:00"}