{"id": "726770", "kind": "single", "title": "Daaru Ft. Sudesh Kumari", "artist": "Samar", "music": "Jassi X", "lyrics": "Raahi", "label": "HMJ Productions", "released": "09-03-2022", "playtime": "03:22", "plays": "11676", "cover": "https://lq.djjohal.com/covers/726770/Daaru.jpg", "detail_url": "https://www.djjohal.com/single/726770/samar-daaru-ft-sudesh-kumari.html", "slug": "samar-daaru-ft-sudesh-kumari", "url_kind": "single", "mp3": {"stream": "https://dl2.djring.com/sd2.djjohal.com/128/511991/Daaru(DJJOhAL.Com).mp3", "kbps320": "https://hd1.djjohal.com/320/511991/Daaru - Samar (DJJOhAL.Com).mp3", "kbps128": "https://sd2.djjohal.com/128/511991/Daaru - Samar (DJJOhAL.Com).mp3", "kbps48": "https://lq.djjohal.com/48/511991/Daaru - Samar (DJJOhAL.Com).mp3", "zip320": "https://hd1.djjohal.com/download/zip/726770/320/Daaru Ft. Sudesh Kumari.zip", "zip128": "https://hd.djjohal.com/download/zip/726770/128/Daaru Ft. Sudesh Kumari.zip"}, "album_tracks": [], "youtube_url": "", "first_seen_at": "2026-05-25T18:19:29+00:00", "last_seen_at": "2026-05-26T14:37:34+00:00"}