{"id": "61020", "kind": "single", "title": "Harvy Sandhu", "artist": "31 Din Peg", "music": "Desi Crew", "lyrics": "Sukhman Heer", "label": "Beat Motion Productions", "released": "10-11-2017", "playtime": "03:14", "plays": "259491", "cover": "https://lq.djjohal.com/covers/61020/31 Din Peg.jpg", "detail_url": "https://www.djjohal.com/single/61020/harvy-sandhu-31-din-peg.html", "slug": "harvy-sandhu-31-din-peg", "url_kind": "single", "mp3": {"stream": "https://dl2.djring.com/sd2.djjohal.com/128/486845/31 Din Peg(DJJOhAL.Com).mp3", "kbps320": "https://hd1.djjohal.com/320/486845/31 Din Peg - Harvy Sandhu (DJJOhAL.Com).mp3", "kbps128": "https://sd2.djjohal.com/128/486845/31 Din Peg - Harvy Sandhu (DJJOhAL.Com).mp3", "kbps48": "https://lq.djjohal.com/48/486845/31 Din Peg - Harvy Sandhu (DJJOhAL.Com).mp3", "zip320": "https://hd1.djjohal.com/download/zip/61020/320/31 Din Peg.zip", "zip128": "https://hd.djjohal.com/download/zip/61020/128/31 Din Peg.zip"}, "album_tracks": [], "youtube_url": "", "first_seen_at": "2026-05-25T18:19:29+00:00", "last_seen_at": "2026-05-27T11:39:39+00:00"}