{"id": "142030", "kind": "single", "title": "Lahnat Hai Aessey Aashiq De", "artist": "Car Maruti Vargi", "music": "", "lyrics": "", "label": "", "released": "", "playtime": "", "plays": "", "cover": "https://lq.djjohal.com/covers/cover/Lahnat Hai Aessey Aashiq De.jpg", "detail_url": "https://www.djjohal.com/get/142030/lahnat-hai-aessey-aashiq-de-harvinder-tandi.html", "slug": "lahnat-hai-aessey-aashiq-de-harvinder-tandi", "url_kind": "get", "mp3": {"stream": "", "kbps320": "", "kbps128": "", "kbps48": "", "zip320": "", "zip128": ""}, "album_tracks": [], "youtube_url": "https://www.youtube.com/watch?v=TnemWL5W4j4", "first_seen_at": "2026-05-31T13:11:07+00:00", "last_seen_at": "2026-05-31T21:01:19+00:00"}