{"id": "327699", "kind": "single", "title": "Tumba", "artist": "Folk N Duet", "music": "", "lyrics": "", "label": "", "released": "", "playtime": "", "plays": "", "cover": "https://lq.djjohal.com/covers/cover/Tumba.jpg", "detail_url": "https://www.djjohal.com/get/327699/tumba-baljinder-babbal.html", "slug": "tumba-baljinder-babbal", "url_kind": "get", "mp3": {"stream": "", "kbps320": "", "kbps128": "", "kbps48": "", "zip320": "", "zip128": ""}, "album_tracks": [], "youtube_url": "https://www.youtube.com/watch?v=HJwxKZ71w10", "first_seen_at": "2026-05-29T21:43:30+00:00", "last_seen_at": "2026-05-30T05:49:56+00:00"}