{"id": "66660", "kind": "single", "title": "Satinder Sartaaj", "artist": "Udaarian Ft. Jatinder Shah", "music": "Jatinder Shah", "lyrics": "Satinder Sartaaj", "label": "Saga Music", "released": "20-07-2018", "playtime": "05:50", "plays": "919074", "cover": "https://lq.djjohal.com/covers/66660/Udaarian.jpg", "detail_url": "https://www.djjohal.com/single/66660/satinder-sartaaj-udaarian-ft-jatinder-shah.html", "slug": "satinder-sartaaj-udaarian-ft-jatinder-shah", "url_kind": "single", "mp3": {"stream": "https://dl2.djring.com/sd2.djjohal.com/128/494212/Udaarian(DJJOhAL.Com).mp3", "kbps320": "https://hd1.djjohal.com/320/494212/Udaarian - Satinder Sartaaj (DJJOhAL.Com).mp3", "kbps128": "https://sd2.djjohal.com/128/494212/Udaarian - Satinder Sartaaj (DJJOhAL.Com).mp3", "kbps48": "https://lq.djjohal.com/48/494212/Udaarian - Satinder Sartaaj (DJJOhAL.Com).mp3", "zip320": "https://hd1.djjohal.com/download/zip/66660/320/Udaarian Ft. Jatinder Shah.zip", "zip128": "https://hd.djjohal.com/download/zip/66660/128/Udaarian Ft. Jatinder Shah.zip"}, "album_tracks": [], "youtube_url": "", "first_seen_at": "2026-05-25T18:19:29+00:00", "last_seen_at": "2026-05-27T11:28:33+00:00"}