{"id": "394791", "kind": "single", "title": "Phullan Di Chhat Hovey", "artist": "Sarwer", "music": "", "lyrics": "", "label": "", "released": "", "playtime": "", "plays": "", "cover": "https://lq.djjohal.com/covers/cover/Phullan Di Chhat Hovey.jpg", "detail_url": "https://www.djjohal.com/get/394791/phullan-di-chhat-hovey-tralochan-lochi.html", "slug": "phullan-di-chhat-hovey-tralochan-lochi", "url_kind": "get", "mp3": {"stream": "", "kbps320": "", "kbps128": "", "kbps48": "", "zip320": "", "zip128": ""}, "album_tracks": [], "youtube_url": "https://www.youtube.com/watch?v=wpb9PxXwe7Y", "first_seen_at": "2026-05-29T02:03:13+00:00", "last_seen_at": "2026-05-29T11:31:39+00:00"}