{"id": "392681", "kind": "single", "title": "Chup Kar Dar Watja", "artist": "The RFAK Session (Remix)", "music": "", "lyrics": "", "label": "", "released": "", "playtime": "", "plays": "", "cover": "https://lq.djjohal.com/covers/cover/Chup Kar Dar Watja.jpg", "detail_url": "https://www.djjohal.com/get/392681/chup-kar-dar-watja-tarli-digital.html", "slug": "chup-kar-dar-watja-tarli-digital", "url_kind": "get", "mp3": {"stream": "", "kbps320": "", "kbps128": "", "kbps48": "", "zip320": "", "zip128": ""}, "album_tracks": [], "youtube_url": "https://www.youtube.com/watch?v=-dHuAl3r2DQ", "first_seen_at": "2026-05-29T02:03:13+00:00", "last_seen_at": "2026-05-29T11:31:39+00:00"}