{"id": "429189", "kind": "single", "title": "Jugni Rebirth", "artist": "Shortlisted", "music": "", "lyrics": "", "label": "", "released": "", "playtime": "", "plays": "", "cover": "https://lq.djjohal.com/covers/cover/Jugni Rebirth.jpg", "detail_url": "https://www.djjohal.com/get/429189/jugni-rebirth-karan-sehmbi-.html", "slug": "jugni-rebirth-karan-sehmbi-", "url_kind": "get", "mp3": {"stream": "", "kbps320": "", "kbps128": "", "kbps48": "", "zip320": "", "zip128": ""}, "album_tracks": [], "youtube_url": "https://www.youtube.com/watch?v=NIEAKEC5qu4", "first_seen_at": "2026-05-28T11:39:56+00:00", "last_seen_at": "2026-05-28T21:49:43+00:00"}