{"id": "734374", "kind": "single", "title": "Story Last Loss", "artist": "Fateh Shergill", "music": "Ary B", "lyrics": "Fateh Shergill", "label": "Fateh Shergill Music", "released": "28-04-2025", "playtime": "02:56", "plays": "14943", "cover": "https://lq.djjohal.com/covers/734374/Story Last Loss.jpg", "detail_url": "https://www.djjohal.com/single/734374/fateh-shergill-story-last-loss.html", "slug": "fateh-shergill-story-last-loss", "url_kind": "single", "mp3": {"stream": "https://dl2.djring.com/sd2.djjohal.com/128/522828/Story Last Loss(DJJOhAL.Com).mp3", "kbps320": "https://hd1.djjohal.com/320/522828/Story Last Loss - Fateh Shergill (DJJOhAL.Com).mp3", "kbps128": "https://sd2.djjohal.com/128/522828/Story Last Loss - Fateh Shergill (DJJOhAL.Com).mp3", "kbps48": "https://lq.djjohal.com/48/522828/Story Last Loss - Fateh Shergill (DJJOhAL.Com).mp3", "zip320": "https://hd1.djjohal.com/download/zip/734374/320/Story Last Loss.zip", "zip128": "https://hd.djjohal.com/download/zip/734374/128/Story Last Loss.zip"}, "album_tracks": [], "youtube_url": "", "first_seen_at": "2026-05-25T15:58:11+00:00", "last_seen_at": "2026-05-25T16:47:40+00:00"}