{"id": "385995", "kind": "single", "title": "Tari Yaad", "artist": "Live Like Loin", "music": "", "lyrics": "", "label": "", "released": "", "playtime": "", "plays": "", "cover": "https://lq.djjohal.com/covers/cover/Tari Yaad.jpg", "detail_url": "https://www.djjohal.com/get/385995/tari-yaad-deep-ladhar.html", "slug": "tari-yaad-deep-ladhar", "url_kind": "get", "mp3": {"stream": "", "kbps320": "", "kbps128": "", "kbps48": "", "zip320": "", "zip128": ""}, "album_tracks": [], "youtube_url": "https://www.youtube.com/watch?v=3_xwnL1PJAQ", "first_seen_at": "2026-05-29T02:03:13+00:00", "last_seen_at": "2026-05-29T17:35:10+00:00"}