{"id": "728745", "kind": "single", "title": "Nal Nal Reh Ke", "artist": "Davinder Dhillon", "music": "Black Virus", "lyrics": "Harj Maan", "label": "Music Tym", "released": "24-11-2022", "playtime": "02:36", "plays": "9189", "cover": "https://lq.djjohal.com/covers/728745/Nal Nal Reh Ke.jpg", "detail_url": "https://www.djjohal.com/single/728745/davinder-dhillon-nal-nal-reh-ke.html", "slug": "davinder-dhillon-nal-nal-reh-ke", "url_kind": "single", "mp3": {"stream": "https://dl2.djring.com/sd2.djjohal.com/128/514575/Nal Nal Reh Ke(DJJOhAL.Com).mp3", "kbps320": "https://hd1.djjohal.com/320/514575/Nal Nal Reh Ke - Davinder Dhillon (DJJOhAL.Com).mp3", "kbps128": "https://sd2.djjohal.com/128/514575/Nal Nal Reh Ke - Davinder Dhillon (DJJOhAL.Com).mp3", "kbps48": "https://lq.djjohal.com/48/514575/Nal Nal Reh Ke - Davinder Dhillon (DJJOhAL.Com).mp3", "zip320": "https://hd1.djjohal.com/download/zip/728745/320/Nal Nal Reh Ke.zip", "zip128": "https://hd.djjohal.com/download/zip/728745/128/Nal Nal Reh Ke.zip"}, "album_tracks": [], "youtube_url": "", "first_seen_at": "2026-05-25T18:19:29+00:00", "last_seen_at": "2026-05-26T07:35:10+00:00"}