{"id": "130233", "kind": "single", "title": "Polle Polle", "artist": "Wicked & Wild", "music": "", "lyrics": "", "label": "", "released": "", "playtime": "", "plays": "", "cover": "https://lq.djjohal.com/covers/cover/Polle Polle.jpg", "detail_url": "https://www.djjohal.com/get/130233/polle-polle-group-holle-holle.html", "slug": "polle-polle-group-holle-holle", "url_kind": "get", "mp3": {"stream": "", "kbps320": "", "kbps128": "", "kbps48": "", "zip320": "", "zip128": ""}, "album_tracks": [], "youtube_url": "https://www.youtube.com/watch?v=awxCEUgYd7U", "first_seen_at": "2026-06-01T06:59:06+00:00", "last_seen_at": "2026-06-01T09:10:08+00:00"}