{"id": "362058", "kind": "single", "title": "Bhangra Fever", "artist": "Punjabi Out Laws CD 2", "music": "", "lyrics": "", "label": "", "released": "", "playtime": "", "plays": "", "cover": "https://lq.djjohal.com/covers/cover/Bhangra Fever.jpg", "detail_url": "https://www.djjohal.com/get/362058/bhangra-fever-the-dhool-crew.html", "slug": "bhangra-fever-the-dhool-crew", "url_kind": "get", "mp3": {"stream": "", "kbps320": "", "kbps128": "", "kbps48": "", "zip320": "", "zip128": ""}, "album_tracks": [], "youtube_url": "https://www.youtube.com/watch?v=ttDjidVeSg8", "first_seen_at": "2026-05-29T21:43:30+00:00", "last_seen_at": "2026-05-29T21:52:50+00:00"}