{"id": "443450", "kind": "single", "title": "Dua Mangi Si", "artist": "Ishq Bewafa", "music": "", "lyrics": "", "label": "", "released": "", "playtime": "", "plays": "", "cover": "https://lq.djjohal.com/covers/cover/Dua Mangi Si.jpg", "detail_url": "https://www.djjohal.com/get/443450/dua-mangi-si-habib-kaler.html", "slug": "dua-mangi-si-habib-kaler", "url_kind": "get", "mp3": {"stream": "", "kbps320": "", "kbps128": "", "kbps48": "", "zip320": "", "zip128": ""}, "album_tracks": [], "youtube_url": "https://www.youtube.com/watch?v=xU8l1-xiZ9c", "first_seen_at": "2026-05-28T11:39:56+00:00", "last_seen_at": "2026-05-28T17:35:05+00:00"}