{"id": "175858", "kind": "single", "title": "Akhan Rahin", "artist": "Dupatta", "music": "", "lyrics": "", "label": "", "released": "", "playtime": "", "plays": "", "cover": "https://lq.djjohal.com/covers/cover/Akhan Rahin.jpg", "detail_url": "https://www.djjohal.com/get/175858/akhan-rahin-various.html", "slug": "akhan-rahin-various", "url_kind": "get", "mp3": {"stream": "", "kbps320": "", "kbps128": "", "kbps48": "", "zip320": "", "zip128": ""}, "album_tracks": [], "youtube_url": "https://www.youtube.com/watch?v=2VlfGKzA3cU", "first_seen_at": "2026-05-31T02:13:44+00:00", "last_seen_at": "2026-05-31T10:07:08+00:00"}