{"id": "735269", "kind": "single", "title": "Parlour", "artist": "Lalka Likhari", "music": "The Real Tune Studio", "lyrics": "Lalka Likhari", "label": "Urban Play Music", "released": "30-09-2025", "playtime": "02:53", "plays": "3997", "cover": "https://lq.djjohal.com/covers/735269/Parlour.jpg", "detail_url": "https://www.djjohal.com/single/735269/lalka-likhari-parlour.html", "slug": "lalka-likhari-parlour", "url_kind": "single", "mp3": {"stream": "https://dl2.djring.com/sd2.djjohal.com/128/524274/Parlour(DJJOhAL.Com).mp3", "kbps320": "https://hd1.djjohal.com/320/524274/Parlour - Lalka Likhari (DJJOhAL.Com).mp3", "kbps128": "https://sd2.djjohal.com/128/524274/Parlour - Lalka Likhari (DJJOhAL.Com).mp3", "kbps48": "https://lq.djjohal.com/48/524274/Parlour - Lalka Likhari (DJJOhAL.Com).mp3", "zip320": "https://hd1.djjohal.com/download/zip/735269/320/Parlour.zip", "zip128": "https://hd.djjohal.com/download/zip/735269/128/Parlour.zip"}, "album_tracks": [], "youtube_url": "", "first_seen_at": "2026-05-25T18:19:29+00:00", "last_seen_at": "2026-05-25T20:56:25+00:00"}