{"id": "432910", "kind": "single", "title": "Ajo Mitro", "artist": "- The New Generation", "music": "", "lyrics": "", "label": "", "released": "", "playtime": "", "plays": "", "cover": "https://lq.djjohal.com/covers/cover/Ajo Mitro.jpg", "detail_url": "https://www.djjohal.com/get/432910/ajo-mitro-.html", "slug": "ajo-mitro-", "url_kind": "get", "mp3": {"stream": "", "kbps320": "", "kbps128": "", "kbps48": "", "zip320": "", "zip128": ""}, "album_tracks": [], "youtube_url": "https://www.youtube.com/watch?v=Cti0VeNXdm8", "first_seen_at": "2026-05-28T11:39:56+00:00", "last_seen_at": "2026-05-28T21:49:43+00:00"}