{"id": "721800", "kind": "single", "title": "Mukh Tera", "artist": "Karamjit Anmol", "music": "Rd Beat", "lyrics": "Zoravar Sidhu", "label": "D World Music", "released": "04-08-2020", "playtime": "03:17", "plays": "87240", "cover": "https://lq.djjohal.com/covers/721800/Mukh Tera.jpg", "detail_url": "https://www.djjohal.com/single/721800/karamjit-anmol-mukh-tera.html", "slug": "karamjit-anmol-mukh-tera", "url_kind": "single", "mp3": {"stream": "https://dl2.djring.com/sd2.djjohal.com/128/505669/Mukh Tera(DJJOhAL.Com).mp3", "kbps320": "https://hd1.djjohal.com/320/505669/Mukh Tera - Karamjit Anmol (DJJOhAL.Com).mp3", "kbps128": "https://sd2.djjohal.com/128/505669/Mukh Tera - Karamjit Anmol (DJJOhAL.Com).mp3", "kbps48": "https://lq.djjohal.com/48/505669/Mukh Tera - Karamjit Anmol (DJJOhAL.Com).mp3", "zip320": "https://hd1.djjohal.com/download/zip/721800/320/Mukh Tera.zip", "zip128": "https://hd.djjohal.com/download/zip/721800/128/Mukh Tera.zip"}, "album_tracks": [], "youtube_url": "", "first_seen_at": "2026-05-25T18:19:29+00:00", "last_seen_at": "2026-05-26T21:50:13+00:00"}