{"id": "405439", "kind": "single", "title": "2Nyte", "artist": "Wrapping Up Twenty-Eleven (Christmas Edition)", "music": "", "lyrics": "", "label": "", "released": "", "playtime": "", "plays": "", "cover": "https://lq.djjohal.com/covers/cover/2Nyte.jpg", "detail_url": "https://www.djjohal.com/get/405439/2nyte-amar-sandhu.html", "slug": "2nyte-amar-sandhu", "url_kind": "get", "mp3": {"stream": "", "kbps320": "", "kbps128": "", "kbps48": "", "zip320": "", "zip128": ""}, "album_tracks": [], "youtube_url": "https://www.youtube.com/watch?v=EiFiAUSXkh8", "first_seen_at": "2026-05-29T02:03:13+00:00", "last_seen_at": "2026-05-29T11:19:07+00:00"}