{"id": "428123", "kind": "single", "title": "Holi", "artist": "Bling In This Holi", "music": "", "lyrics": "", "label": "", "released": "", "playtime": "", "plays": "", "cover": "https://lq.djjohal.com/covers/cover/Holi.jpg", "detail_url": "https://www.djjohal.com/get/428123/holi-jazzy-b.html", "slug": "holi-jazzy-b", "url_kind": "get", "mp3": {"stream": "", "kbps320": "", "kbps128": "", "kbps48": "", "zip320": "", "zip128": ""}, "album_tracks": [], "youtube_url": "https://www.youtube.com/watch?v=U-zNVD1MpuE", "first_seen_at": "2026-05-28T11:39:56+00:00", "last_seen_at": "2026-05-28T21:49:43+00:00"}