{"id": "266644", "kind": "single", "title": "Charka (Ballin)", "artist": "The Underground King Vol 2", "music": "", "lyrics": "", "label": "", "released": "", "playtime": "", "plays": "", "cover": "https://lq.djjohal.com/covers/cover/Charka (Ballin).jpg", "detail_url": "https://www.djjohal.com/get/266644/charka-ballin-dj-king-kang.html", "slug": "charka-ballin-dj-king-kang", "url_kind": "get", "mp3": {"stream": "", "kbps320": "", "kbps128": "", "kbps48": "", "zip320": "", "zip128": ""}, "album_tracks": [], "youtube_url": "https://www.youtube.com/watch?v=el8KHxSOtFI", "first_seen_at": "2026-05-29T21:43:30+00:00", "last_seen_at": "2026-05-30T16:50:57+00:00"}