{"id": "483287", "kind": "single", "title": "Kaal", "artist": "Great Sardar (2017)", "music": "Desi Crew,B Trix,Jaggi Singh", "lyrics": "Various Artists", "label": "Yellow Music", "released": "14-06-2017", "playtime": "04:14", "plays": "271917", "cover": "https://lq.djjohal.com/covers/58496/Kaal.jpg", "detail_url": "https://www.djjohal.com/get/483287/kaal-ranjit-bawa.html", "slug": "kaal-ranjit-bawa", "url_kind": "get", "mp3": {"stream": "https://dl2.djring.com/sd2.djjohal.com/128/483287/Kaal(DJJOhAL.Com).mp3", "kbps320": "https://hd1.djjohal.com/320/483287/Kaal - Ranjit Bawa (DJJOhAL.Com).mp3", "kbps128": "https://sd2.djjohal.com/128/483287/Kaal - Ranjit Bawa (DJJOhAL.Com).mp3", "kbps48": "https://lq.djjohal.com/48/483287/Kaal - Ranjit Bawa (DJJOhAL.Com).mp3", "zip320": "", "zip128": ""}, "album_tracks": [], "youtube_url": "https://www.youtube.com/watch?v=3lfJVhPCYEg", "first_seen_at": "2026-05-27T14:56:05+00:00", "last_seen_at": "2026-05-27T17:20:21+00:00"}