{"id": "304652", "kind": "single", "title": "Sajda", "artist": "Kaun Dilan Diyan Jaane CD 1", "music": "", "lyrics": "", "label": "", "released": "", "playtime": "", "plays": "", "cover": "https://lq.djjohal.com/covers/cover/Sajda.jpg", "detail_url": "https://www.djjohal.com/get/304652/sajda-hans-raj-hans.html", "slug": "sajda-hans-raj-hans", "url_kind": "get", "mp3": {"stream": "", "kbps320": "", "kbps128": "", "kbps48": "", "zip320": "", "zip128": ""}, "album_tracks": [], "youtube_url": "https://www.youtube.com/watch?v=Kl5laztOo7A", "first_seen_at": "2026-05-29T21:43:30+00:00", "last_seen_at": "2026-05-30T10:02:05+00:00"}