{"id": "518467", "kind": "single", "title": "Flower & Saints", "artist": "Prem Dhillon", "music": "Various Artists", "lyrics": "Various Artists", "label": "Prem Dhillon Music", "released": "11-01-2024", "playtime": "03:00", "plays": "33135", "cover": "https://lq.djjohal.com/covers/731389/Flower & Saints.jpg", "detail_url": "https://www.djjohal.com/get/518467/flower-saints-prem-dhillon.html", "slug": "flower-saints-prem-dhillon", "url_kind": "get", "mp3": {"stream": "https://dl2.djring.com/sd2.djjohal.com/128/518467/Flower  Saints(DJJOhAL.Com).mp3", "kbps320": "https://hd1.djjohal.com/320/518467/Flower  Saints - Prem Dhillon (DJJOhAL.Com).mp3", "kbps128": "https://sd2.djjohal.com/128/518467/Flower  Saints - Prem Dhillon (DJJOhAL.Com).mp3", "kbps48": "https://lq.djjohal.com/48/518467/Flower  Saints - Prem Dhillon (DJJOhAL.Com).mp3", "zip320": "", "zip128": ""}, "album_tracks": [], "youtube_url": "https://www.youtube.com/watch?v=8fU2S-2noLo", "first_seen_at": "2026-05-25T00:10:55+00:00", "last_seen_at": "2026-05-25T06:50:57+00:00"}