{"id": "192864", "kind": "single", "title": "Ni Muteyare", "artist": "Teri Yaad", "music": "", "lyrics": "", "label": "", "released": "", "playtime": "", "plays": "", "cover": "https://lq.djjohal.com/covers/cover/Ni Muteyare.jpg", "detail_url": "https://www.djjohal.com/get/192864/ni-muteyare-sunny-brar.html", "slug": "ni-muteyare-sunny-brar", "url_kind": "get", "mp3": {"stream": "", "kbps320": "", "kbps128": "", "kbps48": "", "zip320": "", "zip128": ""}, "album_tracks": [], "youtube_url": "https://www.youtube.com/watch?v=xB6762WJ6MM", "first_seen_at": "2026-05-31T02:13:44+00:00", "last_seen_at": "2026-05-31T07:37:43+00:00"}