{"id": "186421", "kind": "single", "title": "Jida Dil Tut Jaave", "artist": "Sadde Naal", "music": "", "lyrics": "", "label": "", "released": "", "playtime": "", "plays": "", "cover": "https://lq.djjohal.com/covers/cover/Jida Dil Tut Jaave.jpg", "detail_url": "https://www.djjohal.com/get/186421/jida-dil-tut-jaave-teji-padda.html", "slug": "jida-dil-tut-jaave-teji-padda", "url_kind": "get", "mp3": {"stream": "", "kbps320": "", "kbps128": "", "kbps48": "", "zip320": "", "zip128": ""}, "album_tracks": [], "youtube_url": "https://www.youtube.com/watch?v=H_ddbCY8m0g", "first_seen_at": "2026-05-31T02:13:44+00:00", "last_seen_at": "2026-05-31T07:37:43+00:00"}