{"id": "727848", "kind": "single", "title": "Saali Bewkufi", "artist": "Singga", "music": "Fame Muzic", "lyrics": "Singga", "label": "Singga Music", "released": "19-07-2022", "playtime": "02:53", "plays": "42951", "cover": "https://lq.djjohal.com/covers/727848/Saali Bewkufi.jpg", "detail_url": "https://www.djjohal.com/single/727848/singga-saali-bewkufi.html", "slug": "singga-saali-bewkufi", "url_kind": "single", "mp3": {"stream": "https://dl2.djring.com/sd2.djjohal.com/128/513335/Saali Bewkufi(DJJOhAL.Com).mp3", "kbps320": "https://hd1.djjohal.com/320/513335/Saali Bewkufi - Singga (DJJOhAL.Com).mp3", "kbps128": "https://sd2.djjohal.com/128/513335/Saali Bewkufi - Singga (DJJOhAL.Com).mp3", "kbps48": "https://lq.djjohal.com/48/513335/Saali Bewkufi - Singga (DJJOhAL.Com).mp3", "zip320": "https://hd1.djjohal.com/download/zip/727848/320/Saali Bewkufi.zip", "zip128": "https://hd.djjohal.com/download/zip/727848/128/Saali Bewkufi.zip"}, "album_tracks": [], "youtube_url": "", "first_seen_at": "2026-05-25T18:19:29+00:00", "last_seen_at": "2026-05-26T14:37:34+00:00"}