{"id": "431890", "kind": "single", "title": "Teriyan Mulahjedaariyan", "artist": "Teriyan Mulahjedaariyan", "music": "", "lyrics": "", "label": "", "released": "", "playtime": "", "plays": "", "cover": "https://lq.djjohal.com/covers/cover/Teriyan Mulahjedaariyan.jpg", "detail_url": "https://www.djjohal.com/get/431890/teriyan-mulahjedaariyan-mirika-singh.html", "slug": "teriyan-mulahjedaariyan-mirika-singh", "url_kind": "get", "mp3": {"stream": "", "kbps320": "", "kbps128": "", "kbps48": "", "zip320": "", "zip128": ""}, "album_tracks": [], "youtube_url": "https://www.youtube.com/watch?v=Auw1qxPl1Qc", "first_seen_at": "2026-05-28T11:39:56+00:00", "last_seen_at": "2026-05-28T21:49:43+00:00"}