{"id": "719424", "kind": "single", "title": "Double Cross", "artist": "Gurjit Bawa", "music": "Muzik Mine", "lyrics": "Sekhon", "label": "Third Eye", "released": "25-10-2019", "playtime": "03:19", "plays": "38703", "cover": "https://lq.djjohal.com/covers/719424/Double Cross.jpg", "detail_url": "https://www.djjohal.com/single/719424/gurjit-bawa-double-cross.html", "slug": "gurjit-bawa-double-cross", "url_kind": "single", "mp3": {"stream": "https://dl2.djring.com/sd2.djjohal.com/128/502806/Double Cross(DJJOhAL.Com).mp3", "kbps320": "https://hd1.djjohal.com/320/502806/Double Cross - Gurjit Bawa (DJJOhAL.Com).mp3", "kbps128": "https://sd2.djjohal.com/128/502806/Double Cross - Gurjit Bawa (DJJOhAL.Com).mp3", "kbps48": "https://lq.djjohal.com/48/502806/Double Cross - Gurjit Bawa (DJJOhAL.Com).mp3", "zip320": "https://hd1.djjohal.com/download/zip/719424/320/Double Cross.zip", "zip128": "https://hd.djjohal.com/download/zip/719424/128/Double Cross.zip"}, "album_tracks": [], "youtube_url": "", "first_seen_at": "2026-05-25T18:19:29+00:00", "last_seen_at": "2026-05-27T06:23:13+00:00"}