{"id": "42952", "kind": "single", "title": "ZESTTY", "artist": "DARD DILO KE VS STACHE (XPOSE MASHUP)", "music": "Lyrics:", "lyrics": "Label:", "label": "Released: 01-01-2014", "released": "01-01-2014", "playtime": "04:21", "plays": "3148", "cover": "https://lq.djjohal.com/covers/cover/DARD DILO KE VS STACHE (XPOSE MASHUP).jpg", "detail_url": "https://www.djjohal.com/single/42952/zestty-dard-dilo-ke-vs-stache-xpose-mashup.html", "slug": "zestty-dard-dilo-ke-vs-stache-xpose-mashup", "url_kind": "single", "mp3": {"stream": "https://dl2.djring.com/sd2.djjohal.com/128/447861/DARD DILO KE VS STACHE (XPOSE MASHUP)(DJJOhAL.Com).mp3", "kbps320": "https://hd1.djjohal.com/320/447861/DARD DILO KE VS STACHE (XPOSE MASHUP) - ZESTTY (DJJOhAL.Com).mp3", "kbps128": "https://sd2.djjohal.com/128/447861/DARD DILO KE VS STACHE (XPOSE MASHUP) - ZESTTY (DJJOhAL.Com).mp3", "kbps48": "https://lq.djjohal.com/48/447861/DARD DILO KE VS STACHE (XPOSE MASHUP) - ZESTTY (DJJOhAL.Com).mp3", "zip320": "https://hd1.djjohal.com/download/zip/42952/320/DARD DILO KE VS STACHE (XPOSE MASHUP).zip", "zip128": "https://hd.djjohal.com/download/zip/42952/128/DARD DILO KE VS STACHE (XPOSE MASHUP).zip"}, "album_tracks": [], "youtube_url": "", "first_seen_at": "2026-05-25T18:19:29+00:00", "last_seen_at": "2026-05-28T11:28:21+00:00"}