{"id": "518695", "kind": "single", "title": "Dil Karda", "artist": "G Khan", "music": "Various Artists", "lyrics": "Fresh Media Records", "label": "Fresh Media Records", "released": "07-02-2024", "playtime": "02:47", "plays": "12474", "cover": "https://lq.djjohal.com/covers/731551/Dil Karda.jpg", "detail_url": "https://www.djjohal.com/get/518695/dil-karda-g-khan.html", "slug": "dil-karda-g-khan", "url_kind": "get", "mp3": {"stream": "https://dl2.djring.com/sd2.djjohal.com/128/518695/Dil Karda(DJJOhAL.Com).mp3", "kbps320": "https://hd1.djjohal.com/320/518695/Dil Karda - G Khan (DJJOhAL.Com).mp3", "kbps128": "https://sd2.djjohal.com/128/518695/Dil Karda - G Khan (DJJOhAL.Com).mp3", "kbps48": "https://lq.djjohal.com/48/518695/Dil Karda - G Khan (DJJOhAL.Com).mp3", "zip320": "", "zip128": ""}, "album_tracks": [], "youtube_url": "https://www.youtube.com/watch?v=sjdjdQCZpA8", "first_seen_at": "2026-05-25T00:10:55+00:00", "last_seen_at": "2026-05-25T08:11:06+00:00"}